thonnycontrib/ev3dev/__init__.py
thonnycontrib/ev3dev/version.py
thonnycontrib/ev3dev/res/api.gif
thonnycontrib/ev3dev/res/clean.gif
thonnycontrib/ev3dev/res/doc.gif
thonnycontrib/ev3dev/res/flash.gif
thonnycontrib/ev3dev/res/killall.gif
thonnycontrib/ev3dev/res/log.gif
thonnycontrib/ev3dev/res/mirror.gif
thonnycontrib/ev3dev/res/remotedebug.gif
thonnycontrib/ev3dev/res/remoterun.gif
thonnycontrib/ev3dev/res/simulator.gif
thonnycontrib/ev3dev/res/up.gif
thonny_ev3dev-1.0.4.dist-info/LICENSE.txt
thonny_ev3dev-1.0.4.dist-info/METADATA
thonny_ev3dev-1.0.4.dist-info/WHEEL
thonny_ev3dev-1.0.4.dist-info/top_level.txt
thonny_ev3dev-1.0.4.dist-info/RECORD
