Metadata-Version: 2.1
Name: thonny-ev3dev
Version: 1.0.4
Summary: A plug-in which adds EV3 support for Thonny
Home-page: https://github.com/ev3dev-python-tools/thonny-ev3dev
Author: Harco Kuppens
Author-email: h.kuppens@cs.ru.nl
License: MIT
Keywords: IDE education programming EV3 mindstorms lego
Platform: Windows
Platform: macOS
Platform: Linux
Classifier: Environment :: MacOS X
Classifier: Environment :: Win32 (MS Windows)
Classifier: Environment :: X11 Applications
Classifier: Intended Audience :: Developers
Classifier: Intended Audience :: Education
Classifier: Intended Audience :: End Users/Desktop
Classifier: License :: Freeware
Classifier: License :: OSI Approved :: MIT License
Classifier: Natural Language :: English
Classifier: Operating System :: MacOS
Classifier: Operating System :: Microsoft :: Windows
Classifier: Operating System :: POSIX
Classifier: Operating System :: POSIX :: Linux
Classifier: Programming Language :: Python
Classifier: Programming Language :: Python :: 3
Classifier: Programming Language :: Python :: 3 :: Only
Classifier: Programming Language :: Python :: 3.4
Classifier: Programming Language :: Python :: 3.5
Classifier: Programming Language :: Python :: 3.6
Classifier: Topic :: Education
Classifier: Topic :: Software Development
Requires-Python: >=3.6
Requires-Dist: ev3devcmd (==1.0.2)
Requires-Dist: ev3dev2simulator
